Human_Detector_Device/test2/hdd.v
module human_tracking_device (
    input clk,               // Clock signal
    input reset,             // Reset signal
    input human_detected,    // Pulse signal from the human detector
    output reg alarm,        // Alarm LED signal
    output reg [6:0] seg1,   // 7-segment display for units digit
    output reg [6:0] seg2    // 7-segment display for tens digit
);

    // Internal counter to track the number of people
    reg [6:0] counter; // 7-bit counter (0 to 99)

    // 7-segment display encoding (common cathode)
    function [6:0] decode_7segment(input [3:0] digit);
        case (digit)
            4'd0: decode_7segment = 7'b1000000;
            4'd1: decode_7segment = 7'b1111001;
            4'd2: decode_7segment = 7'b0100100;
            4'd3: decode_7segment = 7'b0110000;
            4'd4: decode_7segment = 7'b0011001;
            4'd5: decode_7segment = 7'b0010010;
            4'd6: decode_7segment = 7'b0000010;
            4'd7: decode_7segment = 7'b1111000;
            4'd8: decode_7segment = 7'b0000000;
            4'd9: decode_7segment = 7'b0010000;
            default: decode_7segment = 7'b1111111; // Blank display
        endcase
    endfunction

    // Main logic for counting and alarm
    always @(posedge clk or posedge reset) begin
        if (reset) begin
            counter <= 7'd0;   // Reset the counter
            alarm <= 1'b0;     // Deactivate the alarm
        end else if (human_detected) begin
            if (counter < 7'd80) begin
                counter <= counter + 1; // Increment the counter
            end else begin
                alarm <= 1'b1; // Activate the alarm when counter exceeds 80
            end
        end
    end

    // Update 7-segment displays
    always @(counter) begin
        seg1 = decode_7segment(counter % 10); // Units digit
        seg2 = decode_7segment(counter / 10); // Tens digit
    end

endmodule

Human_Detector_Device/test2/hdd_tb.v
module human_tracking_device_tb;

    // Testbench signals
    reg clk;                // Clock signal
    reg reset;              // Reset signal
    reg human_detected;     // Signal from the human detector
    wire alarm;             // Alarm LED signal
    wire [6:0] seg1;        // 7-segment display for units digit
    wire [6:0] seg2;        // 7-segment display for tens digit

    // Instantiate the DUT (Device Under Test)
    human_tracking_device dut (
        .clk(clk),
        .reset(reset),
        .human_detected(human_detected),
        .alarm(alarm),
        .seg1(seg1),
        .seg2(seg2)
    );

    // Clock generator
    always #5 clk = ~clk; // Generate a 1 kHz clock (10 ns period)

    // Testbench initial block
    initial begin
        // Initialize signals
        clk = 0;
        reset = 1;  // Assert reset
        human_detected = 0;

        // Enable waveform dumping
        $dumpfile("human_tracking_device.vcd");  // Specify the VCD file name
        $dumpvars(0, human_tracking_device_tb);  // Dump all variables

        // Test scenario
        #10 reset = 0;  // Deassert reset
        #20 human_detected = 1; #10 human_detected = 0;  // Detect 1 person
        #20 human_detected = 1; #10 human_detected = 0;  // Detect 2nd person
        repeat (80) begin
            #20 human_detected = 1; #10 human_detected = 0;  // Detect up to 80 people
        end
        #20 human_detected = 1; #10 human_detected = 0;  // Detect 81st person, alarm should activate
        #50 $finish;  // End simulation
    end

endmodule

Human_Detector_Device/test2/human_tracking_device.vcd
$date
	Mon Nov 25 23:56:05 2024
$end
$version
	Icarus Verilog
$end
$timescale
	1s
$end
$scope module human_tracking_device_tb $end
$var wire 7 ! seg2 [6:0] $end
$var wire 7 " seg1 [6:0] $end
$var wire 1 # alarm $end
$var reg 1 $ clk $end
$var reg 1 % human_detected $end
$var reg 1 & reset $end
$scope module dut $end
$var wire 1 $ clk $end
$var wire 1 % human_detected $end
$var wire 1 & reset $end
$var reg 1 # alarm $end
$var reg 7 ' counter [6:0] $end
$var reg 7 ( seg1 [6:0] $end
$var reg 7 ) seg2 [6:0] $end
$scope function decode_7segment $end
$var reg 4 * digit [3:0] $end
$upscope $end
$upscope $end
$upscope $end
$enddefinitions $end
$comment Show the parameter values. $end
$dumpall
$end
#0
$dumpvars
b0 *
b1000000 )
b1000000 (
b0 '
1&
0%
0$
0#
b1000000 "
b1000000 !
$end
#5
1$
#10
0$
0&
#15
1$
#20
0$
#25
1$
#30
0$
1%
#35
b1111001 "
b1111001 (
b0 *
b1 '
1$
#40
0$
0%
#45
1$
#50
0$
#55
1$
#60
0$
1%
#65
b100100 "
b100100 (
b0 *
b10 '
1$
#70
0$
0%
#75
1$
#80
0$
#85
1$
#90
0$
1%
#95
b110000 "
b110000 (
b0 *
b11 '
1$
#100
0$
0%
#105
1$
#110
0$
#115
1$
#120
0$
1%
#125
b11001 "
b11001 (
b0 *
b100 '
1$
#130
0$
0%
#135
1$
#140
0$
#145
1$
#150
0$
1%
#155
b10010 "
b10010 (
b0 *
b101 '
1$
#160
0$
0%
#165
1$
#170
0$
#175
1$
#180
0$
1%
#185
b10 "
b10 (
b0 *
b110 '
1$
#190
0$
0%
#195
1$
#200
0$
#205
1$
#210
0$
1%
#215
b1111000 "
b1111000 (
b0 *
b111 '
1$
#220
0$
0%
#225
1$
#230
0$
#235
1$
#240
0$
1%
#245
b0 "
b0 (
b0 *
b1000 '
1$
#250
0$
0%
#255
1$
#260
0$
#265
1$
#270
0$
1%
#275
b10000 "
b10000 (
b0 *
b1001 '
1$
#280
0$
0%
#285
1$
#290
0$
#295
1$
#300
0$
1%
#305
b1111001 !
b1111001 )
b1 *
b1000000 "
b1000000 (
b1010 '
1$
#310
0$
0%
#315
1$
#320
0$
#325
1$
#330
0$
1%
#335
b1111001 "
b1111001 (
b1011 '
1$
#340
0$
0%
#345
1$
#350
0$
#355
1$
#360
0$
1%
#365
b100100 "
b100100 (
b1 *
b1100 '
1$
#370
0$
0%
#375
1$
#380
0$
#385
1$
#390
0$
1%
#395
b110000 "
b110000 (
b1 *
b1101 '
1$
#400
0$
0%
#405
1$
#410
0$
#415
1$
#420
0$
1%
#425
b11001 "
b11001 (
b1 *
b1110 '
1$
#430
0$
0%
#435
1$
#440
0$
#445
1$
#450
0$
1%
#455
b10010 "
b10010 (
b1 *
b1111 '
1$
#460
0$
0%
#465
1$
#470
0$
#475
1$
#480
0$
1%
#485
b10 "
b10 (
b1 *
b10000 '
1$
#490
0$
0%
#495
1$
#500
0$
#505
1$
#510
0$
1%
#515
b1111000 "
b1111000 (
b1 *
b10001 '
1$
#520
0$
0%
#525
1$
#530
0$
#535
1$
#540
0$
1%
#545
b0 "
b0 (
b1 *
b10010 '
1$
#550
0$
0%
#555
1$
#560
0$
#565
1$
#570
0$
1%
#575
b10000 "
b10000 (
b1 *
b10011 '
1$
#580
0$
0%
#585
1$
#590
0$
#595
1$
#600
0$
1%
#605
b100100 !
b100100 )
b1000000 "
b1000000 (
b10 *
b10100 '
1$
#610
0$
0%
#615
1$
#620
0$
#625
1$
#630
0$
1%
#635
b1111001 "
b1111001 (
b10 *
b10101 '
1$
#640
0$
0%
#645
1$
#650
0$
#655
1$
#660
0$
1%
#665
b100100 "
b100100 (
b10110 '
1$
#670
0$
0%
#675
1$
#680
0$
#685
1$
#690
0$
1%
#695
b110000 "
b110000 (
b10 *
b10111 '
1$
#700
0$
0%
#705
1$
#710
0$
#715
1$
#720
0$
1%
#725
b11001 "
b11001 (
b10 *
b11000 '
1$
#730
0$
0%
#735
1$
#740
0$
#745
1$
#750
0$
1%
#755
b10010 "
b10010 (
b10 *
b11001 '
1$
#760
0$
0%
#765
1$
#770
0$
#775
1$
#780
0$
1%
#785
b10 "
b10 (
b10 *
b11010 '
1$
#790
0$
0%
#795
1$
#800
0$
#805
1$
#810
0$
1%
#815
b1111000 "
b1111000 (
b10 *
b11011 '
1$
#820
0$
0%
#825
1$
#830
0$
#835
1$
#840
0$
1%
#845
b0 "
b0 (
b10 *
b11100 '
1$
#850
0$
0%
#855
1$
#860
0$
#865
1$
#870
0$
1%
#875
b10000 "
b10000 (
b10 *
b11101 '
1$
#880
0$
0%
#885
1$
#890
0$
#895
1$
#900
0$
1%
#905
b110000 !
b110000 )
b1000000 "
b1000000 (
b11 *
b11110 '
1$
#910
0$
0%
#915
1$
#920
0$
#925
1$
#930
0$
1%
#935
b1111001 "
b1111001 (
b11 *
b11111 '
1$
#940
0$
0%
#945
1$
#950
0$
#955
1$
#960
0$
1%
#965
b100100 "
b100100 (
b11 *
b100000 '
1$
#970
0$
0%
#975
1$
#980
0$
#985
1$
#990
0$
1%
#995
b110000 "
b110000 (
b100001 '
1$
#1000
0$
0%
#1005
1$
#1010
0$
#1015
1$
#1020
0$
1%
#1025
b11001 "
b11001 (
b11 *
b100010 '
1$
#1030
0$
0%
#1035
1$
#1040
0$
#1045
1$
#1050
0$
1%
#1055
b10010 "
b10010 (
b11 *
b100011 '
1$
#1060
0$
0%
#1065
1$
#1070
0$
#1075
1$
#1080
0$
1%
#1085
b10 "
b10 (
b11 *
b100100 '
1$
#1090
0$
0%
#1095
1$
#1100
0$
#1105
1$
#1110
0$
1%
#1115
b1111000 "
b1111000 (
b11 *
b100101 '
1$
#1120
0$
0%
#1125
1$
#1130
0$
#1135
1$
#1140
0$
1%
#1145
b0 "
b0 (
b11 *
b100110 '
1$
#1150
0$
0%
#1155
1$
#1160
0$
#1165
1$
#1170
0$
1%
#1175
b10000 "
b10000 (
b11 *
b100111 '
1$
#1180
0$
0%
#1185
1$
#1190
0$
#1195
1$
#1200
0$
1%
#1205
b11001 !
b11001 )
b1000000 "
b1000000 (
b100 *
b101000 '
1$
#1210
0$
0%
#1215
1$
#1220
0$
#1225
1$
#1230
0$
1%
#1235
b1111001 "
b1111001 (
b100 *
b101001 '
1$
#1240
0$
0%
#1245
1$
#1250
0$
#1255
1$
#1260
0$
1%
#1265
b100100 "
b100100 (
b100 *
b101010 '
1$
#1270
0$
0%
#1275
1$
#1280
0$
#1285
1$
#1290
0$
1%
#1295
b110000 "
b110000 (
b100 *
b101011 '
1$
#1300
0$
0%
#1305
1$
#1310
0$
#1315
1$
#1320
0$
1%
#1325
b11001 "
b11001 (
b101100 '
1$
#1330
0$
0%
#1335
1$
#1340
0$
#1345
1$
#1350
0$
1%
#1355
b10010 "
b10010 (
b100 *
b101101 '
1$
#1360
0$
0%
#1365
1$
#1370
0$
#1375
1$
#1380
0$
1%
#1385
b10 "
b10 (
b100 *
b101110 '
1$
#1390
0$
0%
#1395
1$
#1400
0$
#1405
1$
#1410
0$
1%
#1415
b1111000 "
b1111000 (
b100 *
b101111 '
1$
#1420
0$
0%
#1425
1$
#1430
0$
#1435
1$
#1440
0$
1%
#1445
b0 "
b0 (
b100 *
b110000 '
1$
#1450
0$
0%
#1455
1$
#1460
0$
#1465
1$
#1470
0$
1%
#1475
b10000 "
b10000 (
b100 *
b110001 '
1$
#1480
0$
0%
#1485
1$
#1490
0$
#1495
1$
#1500
0$
1%
#1505
b10010 !
b10010 )
b1000000 "
b1000000 (
b101 *
b110010 '
1$
#1510
0$
0%
#1515
1$
#1520
0$
#1525
1$
#1530
0$
1%
#1535
b1111001 "
b1111001 (
b101 *
b110011 '
1$
#1540
0$
0%
#1545
1$
#1550
0$
#1555
1$
#1560
0$
1%
#1565
b100100 "
b100100 (
b101 *
b110100 '
1$
#1570
0$
0%
#1575
1$
#1580
0$
#1585
1$
#1590
0$
1%
#1595
b110000 "
b110000 (
b101 *
b110101 '
1$
#1600
0$
0%
#1605
1$
#1610
0$
#1615
1$
#1620
0$
1%
#1625
b11001 "
b11001 (
b101 *
b110110 '
1$
#1630
0$
0%
#1635
1$
#1640
0$
#1645
1$
#1650
0$
1%
#1655
b10010 "
b10010 (
b110111 '
1$
#1660
0$
0%
#1665
1$
#1670
0$
#1675
1$
#1680
0$
1%
#1685
b10 "
b10 (
b101 *
b111000 '
1$
#1690
0$
0%
#1695
1$
#1700
0$
#1705
1$
#1710
0$
1%
#1715
b1111000 "
b1111000 (
b101 *
b111001 '
1$
#1720
0$
0%
#1725
1$
#1730
0$
#1735
1$
#1740
0$
1%
#1745
b0 "
b0 (
b101 *
b111010 '
1$
#1750
0$
0%
#1755
1$
#1760
0$
#1765
1$
#1770
0$
1%
#1775
b10000 "
b10000 (
b101 *
b111011 '
1$
#1780
0$
0%
#1785
1$
#1790
0$
#1795
1$
#1800
0$
1%
#1805
b10 !
b10 )
b1000000 "
b1000000 (
b110 *
b111100 '
1$
#1810
0$
0%
#1815
1$
#1820
0$
#1825
1$
#1830
0$
1%
#1835
b1111001 "
b1111001 (
b110 *
b111101 '
1$
#1840
0$
0%
#1845
1$
#1850
0$
#1855
1$
#1860
0$
1%
#1865
b100100 "
b100100 (
b110 *
b111110 '
1$
#1870
0$
0%
#1875
1$
#1880
0$
#1885
1$
#1890
0$
1%
#1895
b110000 "
b110000 (
b110 *
b111111 '
1$
#1900
0$
0%
#1905
1$
#1910
0$
#1915
1$
#1920
0$
1%
#1925
b11001 "
b11001 (
b110 *
b1000000 '
1$
#1930
0$
0%
#1935
1$
#1940
0$
#1945
1$
#1950
0$
1%
#1955
b10010 "
b10010 (
b110 *
b1000001 '
1$
#1960
0$
0%
#1965
1$
#1970
0$
#1975
1$
#1980
0$
1%
#1985
b10 "
b10 (
b1000010 '
1$
#1990
0$
0%
#1995
1$
#2000
0$
#2005
1$
#2010
0$
1%
#2015
b1111000 "
b1111000 (
b110 *
b1000011 '
1$
#2020
0$
0%
#2025
1$
#2030
0$
#2035
1$
#2040
0$
1%
#2045
b0 "
b0 (
b110 *
b1000100 '
1$
#2050
0$
0%
#2055
1$
#2060
0$
#2065
1$
#2070
0$
1%
#2075
b10000 "
b10000 (
b110 *
b1000101 '
1$
#2080
0$
0%
#2085
1$
#2090
0$
#2095
1$
#2100
0$
1%
#2105
b1111000 !
b1111000 )
b1000000 "
b1000000 (
b111 *
b1000110 '
1$
#2110
0$
0%
#2115
1$
#2120
0$
#2125
1$
#2130
0$
1%
#2135
b1111001 "
b1111001 (
b111 *
b1000111 '
1$
#2140
0$
0%
#2145
1$
#2150
0$
#2155
1$
#2160
0$
1%
#2165
b100100 "
b100100 (
b111 *
b1001000 '
1$
#2170
0$
0%
#2175
1$
#2180
0$
#2185
1$
#2190
0$
1%
#2195
b110000 "
b110000 (
b111 *
b1001001 '
1$
#2200
0$
0%
#2205
1$
#2210
0$
#2215
1$
#2220
0$
1%
#2225
b11001 "
b11001 (
b111 *
b1001010 '
1$
#2230
0$
0%
#2235
1$
#2240
0$
#2245
1$
#2250
0$
1%
#2255
b10010 "
b10010 (
b111 *
b1001011 '
1$
#2260
0$
0%
#2265
1$
#2270
0$
#2275
1$
#2280
0$
1%
#2285
b10 "
b10 (
b111 *
b1001100 '
1$
#2290
0$
0%
#2295
1$
#2300
0$
#2305
1$
#2310
0$
1%
#2315
b1111000 "
b1111000 (
b1001101 '
1$
#2320
0$
0%
#2325
1$
#2330
0$
#2335
1$
#2340
0$
1%
#2345
b0 "
b0 (
b111 *
b1001110 '
1$
#2350
0$
0%
#2355
1$
#2360
0$
#2365
1$
#2370
0$
1%
#2375
b10000 "
b10000 (
b111 *
b1001111 '
1$
#2380
0$
0%
#2385
1$
#2390
0$
#2395
1$
#2400
0$
1%
#2405
b0 !
b0 )
b1000000 "
b1000000 (
b1000 *
b1010000 '
1$
#2410
0$
0%
#2415
1$
#2420
0$
#2425
1$
#2430
0$
1%
#2435
1#
1$
#2440
0$
0%
#2445
1$
#2450
0$
#2455
1$
#2460
0$
1%
#2465
1$
#2470
0$
0%
#2475
1$
#2480
0$
#2485
1$
#2490
0$
1%
#2495
1$
#2500
0$
0%
